cursofiap/__init__.py
cursofiap/core.py
cursofiap_marinaslucas_2025-1.0.0.dist-info/METADATA
cursofiap_marinaslucas_2025-1.0.0.dist-info/WHEEL
cursofiap_marinaslucas_2025-1.0.0.dist-info/top_level.txt
cursofiap_marinaslucas_2025-1.0.0.dist-info/RECORD
