Metadata-Version: 2.4
Name: cursofiap-marinaslucas-2025
Version: 1.0.0
Summary: Curso de Python da FIAP - IA Para Devs
Home-page: https://github.com/marinaslucas/cursofiap
Author: Marina Altoé
Author-email: aws.developer.studies@gmail.com
License: MIT
Dynamic: author
Dynamic: author-email
Dynamic: description
Dynamic: description-content-type
Dynamic: home-page
Dynamic: license
Dynamic: summary
